twofabackup/__init__.py
twofabackup/main.py
twofabackup-1.1.0.dist-info/LICENSE
twofabackup-1.1.0.dist-info/METADATA
twofabackup-1.1.0.dist-info/WHEEL
twofabackup-1.1.0.dist-info/entry_points.txt
twofabackup-1.1.0.dist-info/RECORD
