Metadata-Version: 2.1
Name: twofabackup
Version: 1.1.0
Summary: Application to safely and locally store backup codes for two factor authenticated services
Home-page: https://github.com/narbux/twofabackup
License: GPL-3.0-or-later
Author: Marnix Enthoven
Author-email: 26323484+narbux@users.noreply.github.com
Requires-Python: >=3.11,<4.0
Classifier: Development Status :: 5 - Production/Stable
Classifier: Environment :: Console
Classifier: License :: OSI Approved :: GNU General Public License v3 or later (GPLv3+)
Classifier: Operating System :: POSIX :: Linux
Classifier: Programming Language :: Python :: 3
Classifier: Programming Language :: Python :: 3.11
Classifier: Programming Language :: Python :: 3.12
Classifier: Topic :: System :: Archiving :: Backup
Classifier: Topic :: Utilities
Requires-Dist: cryptography (>=41.0.7,<42.0.0)
Requires-Dist: rich (>=13.7.0,<14.0.0)
Project-URL: Repository, https://github.com/narbux/twofabackup
